gwseq_io.cpython-313-darwin.so
gwseq_io/bam_entry.cpp
gwseq_io/bam_header.cpp
gwseq_io/bam_index.cpp
gwseq_io/bam_reader.cpp
gwseq_io/bbi_data_tree.cpp
gwseq_io/bbi_data_values.cpp
gwseq_io/bbi_headers.cpp
gwseq_io/bbi_locs.cpp
gwseq_io/bbi_reader.cpp
gwseq_io/binding.cpp
gwseq_io/genomes.cpp
gwseq_io/hic_headers.cpp
gwseq_io/hic_locs.cpp
gwseq_io/hic_matrices_data.cpp
gwseq_io/hic_matrices_metadata.cpp
gwseq_io/hic_reader.cpp
gwseq_io/main.cpp
gwseq_io/util/array_util.cpp
gwseq_io/util/byte_util.cpp
gwseq_io/util/compression_util.cpp
gwseq_io/util/file_util.cpp
gwseq_io/util/includes.cpp
gwseq_io/util/iter_util.cpp
gwseq_io/util/loc_util.cpp
gwseq_io/util/main.cpp
gwseq_io/util/map_util.cpp
gwseq_io/util/parallel_util.cpp
gwseq_io/util/progress_util.cpp
gwseq_io/util/py_call.cpp
gwseq_io/util/py_util.cpp
gwseq_io/util/string_util.cpp
gwseq_io/util/tree_util.cpp
gwseq_io-0.0.14.data/data/gwseq_io/array_util.cpp
gwseq_io-0.0.14.data/data/gwseq_io/bam_entry.cpp
gwseq_io-0.0.14.data/data/gwseq_io/bam_header.cpp
gwseq_io-0.0.14.data/data/gwseq_io/bam_index.cpp
gwseq_io-0.0.14.data/data/gwseq_io/bam_reader.cpp
gwseq_io-0.0.14.data/data/gwseq_io/bbi_data_tree.cpp
gwseq_io-0.0.14.data/data/gwseq_io/bbi_data_values.cpp
gwseq_io-0.0.14.data/data/gwseq_io/bbi_headers.cpp
gwseq_io-0.0.14.data/data/gwseq_io/bbi_locs.cpp
gwseq_io-0.0.14.data/data/gwseq_io/bbi_reader.cpp
gwseq_io-0.0.14.data/data/gwseq_io/binding.cpp
gwseq_io-0.0.14.data/data/gwseq_io/byte_util.cpp
gwseq_io-0.0.14.data/data/gwseq_io/compression_util.cpp
gwseq_io-0.0.14.data/data/gwseq_io/file_util.cpp
gwseq_io-0.0.14.data/data/gwseq_io/genomes.cpp
gwseq_io-0.0.14.data/data/gwseq_io/hic_headers.cpp
gwseq_io-0.0.14.data/data/gwseq_io/hic_locs.cpp
gwseq_io-0.0.14.data/data/gwseq_io/hic_matrices_data.cpp
gwseq_io-0.0.14.data/data/gwseq_io/hic_matrices_metadata.cpp
gwseq_io-0.0.14.data/data/gwseq_io/hic_reader.cpp
gwseq_io-0.0.14.data/data/gwseq_io/includes.cpp
gwseq_io-0.0.14.data/data/gwseq_io/iter_util.cpp
gwseq_io-0.0.14.dist-info/licenses/LICENSE
gwseq_io-0.0.14.dist-info/METADATA
gwseq_io-0.0.14.dist-info/WHEEL
gwseq_io-0.0.14.dist-info/top_level.txt
gwseq_io-0.0.14.dist-info/RECORD
