Metadata-Version: 2.4
Name: gwseq_io
Version: 0.0.14
Summary: Process BBI (bigWig/bigBed) and HiC files
Author-email: Arthur Gouhier <ajgouhier@gmail.com>
License-Expression: MIT
Project-URL: Repository, https://github.com/ajgouhier/gwseq_io
Requires-Python: >=3.8
License-File: LICENSE
Requires-Dist: numpy
Requires-Dist: pybind11>=2.6.0
Dynamic: license-file
